[
  {
    "id": 0,
    "name": "بِسْمِ اللَّهِ الرَّحْمَٰنِ الرَّحِيمِ"
  },
  {
    "id": 1,
    "name": "أَلْهَاكُمُ التَّكَاثُرُ"
  },
  {
    "id": 2,
    "name": "حَتَّىٰ زُرْتُمُ الْمَقَابِرَ"
  },
  {
    "id": 3,
    "name": "كَلَّا سَوْفَ تَعْلَمُونَ"
  },
  {
    "id": 4,
    "name": "ثُمَّ كَلَّا سَوْفَ تَعْلَمُونَ"
  },
  {
    "id": 5,
    "name": "كَلَّا لَوْ تَعْلَمُونَ عِلْمَ الْيَقِينِ"
  },
  {
    "id": 6,
    "name": "لَتَرَوُنَّ الْجَحِيمَ"
  },
  {
    "id": 7,
    "name": "ثُمَّ لَتَرَوُنَّهَا عَيْنَ الْيَقِينِ"
  },
  {
    "id": 8,
    "name": "ثُمَّ لَتُسْأَلُنَّ يَوْمَئِذٍ عَنِ النَّعِيمِ"
  }
]